{"token_views": {"Avicii": 24795, "Tribute": 24795, "HARRY": 33659, "STYLES": 33659, "7": 33659, "Lovely": 43123, "SOUL": 43123, ",": 43123, "R": 43123, "B": 43123, "JAZZ": 43123, "Music": 43123, "RASPY": 43213, "Young": 43741, "with": 43741, "MATURE": 43741, "POPULAR": 46405, "DISNEY": 46405, "\ud83d\udc2d": 46405, "TAYLOR": 48486, "SWIFT": 48486, "Covers": 48486, "CUTEST": 52418, "ADORABLE": 52418, "\ud83e\udd7a": 52418, "2000s": 52692, "POLAND": 53032, "\ud83c\uddf5\ud83c\uddf1": 53032, "CRAZIEST": 56327, "\ud83e\udd2a": 56327, "MOVIE": 58482, "SOUNDTRACKS": 58482, "\ud83c\udf7f": 58482, "DANCERS": 67659, "\ud83d\udc83\ud83c\udffb": 67659, "These": 68300, "performances": 68300, "will": 68300, "give": 68300, "you": 68300, "GOOSEBUMPS": 68300, "&": 86336, "COVERS": 94666, "worldwide": 94776, "update": 94776, "Most": 98823, "GROOVIEST": 100166, "70s": 100166, "80s": 100166, "\ud83c\udf3c": 100166, "INSANE": 101242, "ROCK": 101242, "Songs": 101242, "the": 101242, "\ud83e\udd18": 101242, "\ud83e\udd70": 111423, "INCREDIBLE": 120992, "UNFORGETTABLE": 123364, "UNIQUE": 137879, "JAW-DROPPING": 154205, "\ud83d\ude32": 154205, "\ud83e\udd2f": 166577, "UNEXPECTED": 167779, "SURPRISING": 167779, "QUICKEST": 167802, "TURNS": 167802, "\ud83d\ude0d": 176811, "songs": 199263, "turn": 238205, "into": 238205, "CONCERTS": 238205, "VOICES": 254733, "UNBELIEVABLE": 291373, "MOST": 305406, "VIEWED": 305406, "so": 333994, "far": 333994, "\ud83d\ude0e": 347118, "GREATEST": 351613, "ALL": 351613, "TURN": 351613, "BOYS": 390859, "BELGIUM": 419799, "Vlaanderen": 419799, "\u2764\ufe0f": 444594, "and": 463652, "CHAIR": 519415, "on": 595903, "GERMANY": 757164, "BLIND": 834400, "AUDITIONS": 834400, "\ud83d\ude31": 868539, "Part": 955186, "2": 955186, "GIRLS": 1004561, "\ud83d\udc96": 1004561, "6": 1181406, "Blind": 1312584, "Auditions": 1312584, "\ud83e\udd29": 1339434, "ever": 1356174, "2022": 1711183, "of": 1744842, "(": 1803755, ")": 1803755, "in": 2804446, "BEST": 2831644, "10": 4101730, "Kids": 4640494, "Voice": 4886926, "The": 4935412, "!": 5193431, "|": 5316795, "Top": 5316795}, "token_counts": {"Young": 1, "with": 1, "MATURE": 1, "JAW-DROPPING": 1, "\ud83d\ude32": 1, "TAYLOR": 1, "SWIFT": 1, "Covers": 1, "turn": 1, "into": 1, "CONCERTS": 1, "CUTEST": 1, "ADORABLE": 1, "\ud83e\udd7a": 1, "Lovely": 1, "SOUL": 1, ",": 1, "R": 1, "B": 1, "JAZZ": 1, "Music": 1, "QUICKEST": 1, "TURNS": 1, "HARRY": 1, "STYLES": 1, "7": 1, "POPULAR": 1, "DISNEY": 1, "\ud83d\udc2d": 1, "MOVIE": 1, "SOUNDTRACKS": 1, "\ud83c\udf7f": 1, "UNFORGETTABLE": 1, "UNEXPECTED": 1, "SURPRISING": 1, "BELGIUM": 1, "Vlaanderen": 1, "RASPY": 1, "CRAZIEST": 1, "\ud83e\udd2a": 1, "Avicii": 1, "Tribute": 1, "GERMANY": 1, "2000s": 1, "POLAND": 1, "\ud83c\uddf5\ud83c\uddf1": 1, "COVERS": 1, "GROOVIEST": 1, "70s": 1, "80s": 1, "\ud83c\udf3c": 1, "DANCERS": 1, "\ud83d\udc83\ud83c\udffb": 1, "worldwide": 1, "update": 1, "These": 1, "performances": 1, "will": 1, "give": 1, "you": 1, "GOOSEBUMPS": 1, "\ud83d\ude0e": 1, "INSANE": 1, "ROCK": 1, "Songs": 1, "the": 1, "\ud83e\udd18": 1, "GIRLS": 1, "\ud83d\udc96": 1, "UNBELIEVABLE": 1, "GREATEST": 1, "ALL": 1, "TURN": 1, "BOYS": 2, "Most": 2, "&": 2, "\ud83e\udd70": 2, "CHAIR": 2, "MOST": 2, "VIEWED": 2, "so": 2, "far": 2, "\ud83e\udd2f": 2, "\u2764\ufe0f": 2, "UNIQUE": 2, "INCREDIBLE": 2, "ever": 2, "VOICES": 3, "\ud83d\ude0d": 3, "songs": 3, "BLIND": 4, "AUDITIONS": 4, "\ud83e\udd29": 4, "\ud83d\ude31": 5, "and": 5, "Part": 6, "2": 6, "2022": 7, "on": 8, "Blind": 8, "Auditions": 8, "of": 8, "BEST": 9, "(": 10, ")": 10, "6": 13, "in": 14, "10": 16, "Kids": 24, "Voice": 27, "The": 28, "!": 29, "|": 30, "Top": 30}, "term_views": {"Avicii": 24795, "Tribute": 24795, "HARRY": 33659, "STYLES": 33659, "7": 33659, "Lovely": 43123, "SOUL,": 43123, "R&B": 43123, "JAZZ": 43123, "Music": 43123, "RASPY": 43213, "&": 43213, "Young": 43741, "with": 43741, "MATURE": 43741, "POPULAR": 46405, "DISNEY": 46405, "\ud83d\udc2d": 46405, "TAYLOR": 48486, "SWIFT": 48486, "Covers": 48486, "CUTEST": 52418, "ADORABLE": 52418, "\ud83e\udd7a": 52418, "2000s": 52692, "POLAND": 53032, "\ud83c\uddf5\ud83c\uddf1": 53032, "CRAZIEST": 56327, "\ud83e\udd2a": 56327, "MOVIE": 58482, "SOUNDTRACKS": 58482, "\ud83c\udf7f": 58482, "DANCERS": 67659, "\ud83d\udc83\ud83c\udffb": 67659, "These": 68300, "performances": 68300, "will": 68300, "give": 68300, "you": 68300, "GOOSEBUMPS!": 68300, "COVERS": 94666, "worldwide!": 94776, "(2022": 94776, "update)": 94776, "Most": 98823, "GROOVIEST": 100166, "70s": 100166, "80s": 100166, "\ud83c\udf3c": 100166, "INSANE": 101242, "ROCK": 101242, "Songs": 101242, "the": 101242, "\ud83e\udd18": 101242, "\ud83e\udd70": 111423, "INCREDIBLE": 120992, "UNFORGETTABLE": 123364, "UNIQUE": 137879, "JAW-DROPPING": 154205, "\ud83d\ude32": 154205, "\ud83e\udd2f": 166577, "UNEXPECTED": 167779, "SURPRISING": 167779, "QUICKEST": 167802, "TURNS": 167802, "\ud83d\ude0d": 176811, "songs": 199263, "turn": 238205, "into": 238205, "CONCERTS!": 238205, "Voice!": 246432, "VOICES": 254733, "UNBELIEVABLE": 291373, "MOST": 305406, "VIEWED": 305406, "(so": 333994, "far)": 333994, "\ud83d\ude0e": 347118, "GREATEST": 351613, "ALL": 351613, "TURN": 351613, "ever!": 351613, "BOYS": 390859, "BELGIUM": 419799, "(Vlaanderen)!": 419799, "\u2764\ufe0f": 444594, "and": 463652, "CHAIR": 519415, "2022": 543163, "on": 595903, "GERMANY": 757164, "BLIND": 834400, "AUDITIONS": 834400, "\ud83d\ude31": 868539, "(Part": 955186, "2)": 955186, "GIRLS": 1004561, "ever": 1004561, "\ud83d\udc96": 1004561, "2022!": 1073244, "6": 1181406, "Blind": 1312584, "Auditions": 1312584, "\ud83e\udd29": 1339434, "of": 1744842, "Kids": 1939432, "Kids!": 2701062, "in": 2804446, "BEST": 2831644, "10": 4101730, "Voice": 4640494, "The": 4935412, "|": 5316795, "Top": 5316795}, "term_counts": {"Young": 1, "with": 1, "MATURE": 1, "JAW-DROPPING": 1, "\ud83d\ude32": 1, "TAYLOR": 1, "SWIFT": 1, "Covers": 1, "turn": 1, "into": 1, "CONCERTS!": 1, "CUTEST": 1, "ADORABLE": 1, "\ud83e\udd7a": 1, "Lovely": 1, "SOUL,": 1, "R&B": 1, "JAZZ": 1, "Music": 1, "QUICKEST": 1, "TURNS": 1, "HARRY": 1, "STYLES": 1, "7": 1, "POPULAR": 1, "DISNEY": 1, "\ud83d\udc2d": 1, "MOVIE": 1, "SOUNDTRACKS": 1, "\ud83c\udf7f": 1, "UNFORGETTABLE": 1, "UNEXPECTED": 1, "SURPRISING": 1, "BELGIUM": 1, "(Vlaanderen)!": 1, "RASPY": 1, "&": 1, "CRAZIEST": 1, "\ud83e\udd2a": 1, "Avicii": 1, "Tribute": 1, "GERMANY": 1, "2000s": 1, "POLAND": 1, "\ud83c\uddf5\ud83c\uddf1": 1, "COVERS": 1, "GROOVIEST": 1, "70s": 1, "80s": 1, "\ud83c\udf3c": 1, "DANCERS": 1, "\ud83d\udc83\ud83c\udffb": 1, "worldwide!": 1, "(2022": 1, "update)": 1, "These": 1, "performances": 1, "will": 1, "give": 1, "you": 1, "GOOSEBUMPS!": 1, "\ud83d\ude0e": 1, "INSANE": 1, "ROCK": 1, "Songs": 1, "the": 1, "\ud83e\udd18": 1, "GIRLS": 1, "ever": 1, "\ud83d\udc96": 1, "UNBELIEVABLE": 1, "GREATEST": 1, "ALL": 1, "TURN": 1, "ever!": 1, "BOYS": 2, "Most": 2, "\ud83e\udd70": 2, "CHAIR": 2, "MOST": 2, "VIEWED": 2, "(so": 2, "far)": 2, "2022": 2, "\ud83e\udd2f": 2, "\u2764\ufe0f": 2, "UNIQUE": 2, "INCREDIBLE": 2, "VOICES": 3, "Voice!": 3, "\ud83d\ude0d": 3, "songs": 3, "BLIND": 4, "AUDITIONS": 4, "\ud83e\udd29": 4, "2022!": 4, "\ud83d\ude31": 5, "and": 5, "(Part": 6, "2)": 6, "Kids": 7, "on": 8, "Blind": 8, "Auditions": 8, "of": 8, "BEST": 9, "6": 13, "in": 14, "10": 16, "Kids!": 17, "Voice": 24, "The": 28, "|": 30, "Top": 30}}