{"token_views": {"Fix": 2620, "Flipped": 2620, "Screen": 2620, "Rotation": 2620, "Testing": 2940, "GPU": 2940, "3": 2964, "Huge": 2964, "Announcements": 2964, "Discord": 2964, "&": 2964, "Garage": 2964, "Sale": 2964, "Programming": 3617, "the": 3617, "Help": 3617, "of": 3617, "AI": 3617, "called": 3617, "CoPilot": 3617, "Github": 3617, "Quick": 3625, "Pi-KVM": 3625, "Update": 3625, "Audio": 3625, "Pass-through": 3625, "Massive": 3712, "Resin": 3712, "3D": 3712, "Printer": 3712, "by": 3712, "Elegoo": 3712, "Saturn": 3712, "Out": 3987, "BIQU": 3987, "PAD": 3987, "5": 3987, "CM4": 3987, "seeed": 4052, "studio": 4052, "reComputer": 4052, "Jetson": 4052, "Nano": 4052, "KUU": 4722, "Lebook": 4722, "Pro": 4722, "12.6": 4722, "in": 4722, "1": 4722, "Laptop": 4722, "3:2": 4722, "aspect": 4722, "ratio": 4722, "To": 4879, "Install": 4879, "Imager": 4879, "Beta": 4879, "Bootloader": 4879, "Minimalist": 5023, "Case": 5023, "JC": 5023, "Protec": 5023, "VM": 5208, "ZIMA": 5208, "BOARD": 5208, "Window": 5572, "TS-253D": 5572, "NAS": 5572, "ZimaBoard": 5880, "Giveaway": 5904, "Arducam": 6146, "64": 6146, "MegaPixel": 6146, "Auto": 6146, "Focusing": 6146, "Camera": 6146, "Upgrading": 6310, "20.04": 6310, "Quad": 6887, "Sata": 6887, "Systemd": 6887, "Automount": 6887, "How": 7499, "Geekom": 7687, "IT8": 7687, "vs": 7687, "Intel": 7687, "NUC": 7687, ":": 8051, "Beginners": 8051, "Guide": 8051, "WireGuard": 8051, "Docker": 8051, "Pi-OS": 8051, "64bit": 8051, "Khadas": 8303, "Vim": 8303, "8": 8303, "Core": 8303, "ARM": 8303, "Enabling": 8312, "New": 8312, "UI": 8312, "2": 8434, "from": 9927, "Android": 10209, "Apps": 10209, "Natively": 10209, "Pi-Hosted": 11015, "This": 11253, "Trick": 11253, "Allows": 11253, "You": 11253, "Extend": 11253, "Display": 11253, "any": 11253, "Device": 11253, "SBC": 11267, "Remote": 11649, "Desktop": 11649, "Solutions": 11649, "Building": 11703, "Own": 11703, "Console": 11703, "Review": 11928, "Switching": 13635, "Fedora": 13635, "36": 13635, "Here": 13635, "Is": 13635, "What": 13635, "Learned": 13635, "or": 13884, "your": 13884, "PC": 13997, "Mini": 15374, "Running": 15417, "On": 16825, "PiMox": 16963, "Adobe": 17210, "PhotoShop": 17210, "CC": 17210, "2021": 17210, "For": 17795, "tried": 19543, "days": 19543, "Steam": 20015, "Deck": 20015, "Proxmox": 22171, "Downsizing": 22765, "Server": 22765, "into": 22765, "a": 22765, "TS-364": 22765, "Your": 22956, "OS": 22956, "out": 23388, "for": 23530, "First": 24226, "Impressions": 24226, "4": 25266, "Checking": 27375, "QNAP": 28337, "My": 29075, "11": 29752, "Ubuntu": 30536, "22.04": 30536, "Jammy": 30536, "Jellyfish": 30536, "I": 33178, "-": 36136, "7": 36506, "Windows": 38064, "to": 41869, "with": 45153, "Linux": 45363, "Installing": 47796, "and": 58644, "Raspberry": 79306, "on": 80065, "Pi": 91216, "!": 111089}, "token_counts": {"Quick": 1, "Pi-KVM": 1, "Update": 1, "Audio": 1, "Pass-through": 1, "Programming": 1, "the": 1, "Help": 1, "of": 1, "AI": 1, "called": 1, "CoPilot": 1, "Github": 1, "This": 1, "Trick": 1, "Allows": 1, "You": 1, "Extend": 1, "Display": 1, "any": 1, "Device": 1, "Switching": 1, "Fedora": 1, "36": 1, "Here": 1, "Is": 1, "What": 1, "Learned": 1, "Massive": 1, "Resin": 1, "3D": 1, "Printer": 1, "by": 1, "Elegoo": 1, "Saturn": 1, "seeed": 1, "studio": 1, "reComputer": 1, "Jetson": 1, "Nano": 1, "Quad": 1, "Sata": 1, "Systemd": 1, "Automount": 1, "Building": 1, "Own": 1, "Console": 1, "Out": 1, "BIQU": 1, "PAD": 1, "5": 1, "CM4": 1, "Khadas": 1, "Vim": 1, "8": 1, "Core": 1, "ARM": 1, "Remote": 1, "Desktop": 1, "Solutions": 1, "Upgrading": 1, "20.04": 1, "Arducam": 1, "64": 1, "MegaPixel": 1, "Auto": 1, "Focusing": 1, "Camera": 1, "PiMox": 1, "Testing": 1, "GPU": 1, "To": 1, "Install": 1, "Imager": 1, "Beta": 1, "Bootloader": 1, "Geekom": 1, "IT8": 1, "vs": 1, "Intel": 1, "NUC": 1, "First": 1, "Impressions": 1, "Downsizing": 1, "Server": 1, "into": 1, "a": 1, "TS-364": 1, "Android": 1, "Apps": 1, "Natively": 1, "tried": 1, "days": 1, ":": 1, "Beginners": 1, "Guide": 1, "WireGuard": 1, "Docker": 1, "Pi-OS": 1, "64bit": 1, "Window": 1, "TS-253D": 1, "NAS": 1, "3": 1, "Huge": 1, "Announcements": 1, "Discord": 1, "&": 1, "Garage": 1, "Sale": 1, "Minimalist": 1, "Case": 1, "JC": 1, "Protec": 1, "Fix": 1, "Flipped": 1, "Screen": 1, "Rotation": 1, "KUU": 1, "Lebook": 1, "Pro": 1, "12.6": 1, "in": 1, "1": 1, "Laptop": 1, "3:2": 1, "aspect": 1, "ratio": 1, "Enabling": 1, "New": 1, "UI": 1, "Adobe": 1, "PhotoShop": 1, "CC": 1, "2021": 1, "VM": 1, "ZIMA": 1, "BOARD": 1, "Review": 2, "from": 2, "Your": 2, "On": 2, "OS": 2, "I": 2, "2": 2, "Steam": 2, "Deck": 2, "for": 2, "4": 2, "SBC": 2, "For": 2, "My": 2, "PC": 2, "Ubuntu": 2, "22.04": 2, "Jammy": 2, "Jellyfish": 2, "Proxmox": 2, "7": 2, "ZimaBoard": 2, "Giveaway": 2, "How": 2, "Mini": 2, "QNAP": 2, "Running": 2, "11": 2, "Pi-Hosted": 2, "or": 2, "your": 2, "out": 3, "-": 3, "Windows": 3, "Checking": 4, "Installing": 4, "to": 5, "and": 5, "Linux": 5, "with": 6, "Raspberry": 7, "on": 7, "Pi": 9, "!": 14}, "term_views": {"Fix": 2620, "Flipped": 2620, "Screen": 2620, "Rotation": 2620, "Testing": 2940, "GPU": 2940, "3": 2964, "Huge": 2964, "Announcements!!": 2964, "Discord": 2964, "Pi-Hosted!!": 2964, "&": 2964, "Garage": 2964, "Sale!": 2964, "Programming": 3617, "the": 3617, "Help": 3617, "of": 3617, "AI": 3617, "called": 3617, "CoPilot": 3617, "Github": 3617, "Quick": 3625, "Pi-KVM": 3625, "Update!": 3625, "Audio": 3625, "Pass-through": 3625, "Massive": 3712, "Resin": 3712, "3D": 3712, "Printer": 3712, "by": 3712, "Elegoo": 3712, "Saturn": 3712, "Out": 3987, "BIQU": 3987, "PAD": 3987, "5": 3987, "CM4": 3987, "seeed": 4052, "studio": 4052, "reComputer": 4052, "Jetson": 4052, "Nano": 4052, "KUU": 4722, "Lebook": 4722, "Pro": 4722, "12.6": 4722, "in": 4722, "1": 4722, "Laptop": 4722, "3:2": 4722, "aspect": 4722, "ratio": 4722, "To": 4879, "Install": 4879, "Imager": 4879, "Beta": 4879, "Bootloader": 4879, "Minimalist": 5023, "Case": 5023, "JC": 5023, "Protec": 5023, "VM": 5208, "ZIMA": 5208, "BOARD": 5208, "Window": 5572, "TS-253D": 5572, "NAS": 5572, "ZimaBoard": 5880, "Giveaway!": 5904, "Arducam": 6146, "64": 6146, "MegaPixel": 6146, "Auto": 6146, "Focusing": 6146, "Camera": 6146, "Upgrading": 6310, "20.04": 6310, "Quad": 6887, "Sata": 6887, "Systemd": 6887, "Automount": 6887, "How": 7499, "Geekom": 7687, "IT8": 7687, "vs": 7687, "Intel": 7687, "NUC": 7687, "Pi-Hosted:": 8051, "Beginners": 8051, "Guide": 8051, "WireGuard": 8051, "Docker": 8051, "Pi-OS": 8051, "64bit": 8051, "Khadas": 8303, "Vim": 8303, "8": 8303, "Core": 8303, "ARM": 8303, "Enabling": 8312, "New": 8312, "UI": 8312, "Windows!": 8312, "2": 8434, "from": 9927, "Android": 10209, "Apps": 10209, "Natively": 10209, "This": 11253, "Trick": 11253, "Allows": 11253, "You": 11253, "Extend": 11253, "Display": 11253, "any": 11253, "OS": 11253, "Device!": 11253, "SBC": 11267, "Remote": 11649, "Desktop": 11649, "Solutions": 11649, "Building": 11703, "Own": 11703, "Console": 11703, "OS!!": 11703, "Review": 11928, "Switching": 13635, "Fedora": 13635, "36": 13635, "Here": 13635, "Is": 13635, "What": 13635, "Learned": 13635, "or": 13884, "your": 13884, "PC": 13997, "Mini": 15374, "Running": 15417, "On": 16825, "PiMox": 16963, "Adobe": 17210, "PhotoShop": 17210, "CC": 17210, "2021": 17210, "For": 17795, "tried": 19543, "days!": 19543, "Steam": 20015, "Deck": 20015, "Proxmox": 22171, "Downsizing": 22765, "Server": 22765, "into": 22765, "a": 22765, "TS-364": 22765, "Your": 22956, "out": 23388, "for": 23530, "First": 24226, "Impressions!": 24226, "4": 25266, "Checking": 27375, "QNAP": 28337, "My": 29075, "Windows": 29752, "11": 29752, "Ubuntu": 30536, "22.04": 30536, "Jammy": 30536, "Jellyfish": 30536, "I": 33178, "-": 36136, "7": 36506, "to": 41869, "with": 45153, "Linux": 45363, "Installing": 47796, "and": 58644, "Raspberry": 79306, "on": 80065, "Pi": 91216}, "term_counts": {"Quick": 1, "Pi-KVM": 1, "Update!": 1, "Audio": 1, "Pass-through": 1, "Programming": 1, "the": 1, "Help": 1, "of": 1, "AI": 1, "called": 1, "CoPilot": 1, "Github": 1, "This": 1, "Trick": 1, "Allows": 1, "You": 1, "Extend": 1, "Display": 1, "any": 1, "OS": 1, "Device!": 1, "Switching": 1, "Fedora": 1, "36": 1, "Here": 1, "Is": 1, "What": 1, "Learned": 1, "Massive": 1, "Resin": 1, "3D": 1, "Printer": 1, "by": 1, "Elegoo": 1, "Saturn": 1, "seeed": 1, "studio": 1, "reComputer": 1, "Jetson": 1, "Nano": 1, "Quad": 1, "Sata": 1, "Systemd": 1, "Automount": 1, "Building": 1, "Own": 1, "Console": 1, "OS!!": 1, "Out": 1, "BIQU": 1, "PAD": 1, "5": 1, "CM4": 1, "Khadas": 1, "Vim": 1, "8": 1, "Core": 1, "ARM": 1, "Remote": 1, "Desktop": 1, "Solutions": 1, "Upgrading": 1, "20.04": 1, "Arducam": 1, "64": 1, "MegaPixel": 1, "Auto": 1, "Focusing": 1, "Camera": 1, "PiMox": 1, "Testing": 1, "GPU": 1, "To": 1, "Install": 1, "Imager": 1, "Beta": 1, "Bootloader": 1, "Geekom": 1, "IT8": 1, "vs": 1, "Intel": 1, "NUC": 1, "First": 1, "Impressions!": 1, "Downsizing": 1, "Server": 1, "into": 1, "a": 1, "TS-364": 1, "Android": 1, "Apps": 1, "Natively": 1, "tried": 1, "days!": 1, "Pi-Hosted:": 1, "Beginners": 1, "Guide": 1, "WireGuard": 1, "Docker": 1, "Pi-OS": 1, "64bit": 1, "Window": 1, "TS-253D": 1, "NAS": 1, "3": 1, "Huge": 1, "Announcements!!": 1, "Discord": 1, "Pi-Hosted!!": 1, "&": 1, "Garage": 1, "Sale!": 1, "Minimalist": 1, "Case": 1, "JC": 1, "Protec": 1, "Fix": 1, "Flipped": 1, "Screen": 1, "Rotation": 1, "KUU": 1, "Lebook": 1, "Pro": 1, "12.6": 1, "in": 1, "1": 1, "Laptop": 1, "3:2": 1, "aspect": 1, "ratio": 1, "Enabling": 1, "New": 1, "UI": 1, "Windows!": 1, "Adobe": 1, "PhotoShop": 1, "CC": 1, "2021": 1, "VM": 1, "ZIMA": 1, "BOARD": 1, "Review": 2, "from": 2, "Your": 2, "On": 2, "I": 2, "2": 2, "Steam": 2, "Deck": 2, "for": 2, "4": 2, "SBC": 2, "For": 2, "My": 2, "PC": 2, "Ubuntu": 2, "22.04": 2, "Jammy": 2, "Jellyfish": 2, "Proxmox": 2, "7": 2, "ZimaBoard": 2, "Giveaway!": 2, "How": 2, "Mini": 2, "QNAP": 2, "Running": 2, "Windows": 2, "11": 2, "or": 2, "your": 2, "out": 3, "-": 3, "Checking": 4, "Installing": 4, "to": 5, "and": 5, "Linux": 5, "with": 6, "Raspberry": 7, "on": 7, "Pi": 9}}