{"token_views": {"|": 1322028, ",": 1267784, "in": 1124004, "my": 995521, "life": 965186, "!": 827798, "week": 543866, "&": 529440, "NYC": 514249, "weekend": 401366, "a": 329021, "with": 318832, "days": 307665, "friends": 263660, "of": 259959, "for": 218930, "nyc": 215037, "haul": 212954, "spring": 211725, "getting": 178602, "shopping": 169918, "vlog": 154328, "show": 153041, "out": 149463, "the": 148621, "new": 144934, "night": 142961, "events": 134972, "VLOG": 121470, "holiday": 118882, "snow": 117614, "storm": 117614, "lots": 117614, "reading": 117614, "espresso": 117614, "martinis": 117614, "thrift": 114247, "time": 111179, "cat": 109551, "(": 108770, ")": 108770, "home": 107971, "vacation": 106534, "laser": 104818, "tattoo": 104818, "removal": 104818, "exhibit": 103384, "at": 102305, "vlogmas": 99176, "on": 93600, "cleaning": 90455, "trip": 85804, "day": 78651, "Italy": 76445, "flying": 73747, "to": 73747, "riding": 69577, "prepping": 64795, "lash": 64795, "lift": 64795, "prep": 62867, "christmas": 62867, "decorating": 62867, "cookies": 62867, "rug": 62463, "reveal": 62463, "apartment": 62463, "banksy": 62463, "taking": 59835, "myself": 59835, "quality": 59835, "friends/family": 59835, "+": 59835, "movies": 56706, "advent": 56706, "calendar": 56706, "live": 56706, "mini": 56706, "weather": 56269, "internet": 56269, "IRL": 56269, "update": 56269, "VLOGMAS": 56015, "?": 56015, "black": 56015, "friday": 56015, "hauls": 56015, "winter": 56015, "rooftop": 56015, "bar": 56015, "lights": 56015, "MET": 54412, "date": 54412, "emotional": 54412, "beauty": 52845, "products": 52845, "brunches": 52845, "outfits": 52845, "sitting": 52845, "bf": 51344, "holy": 51344, "grail": 51344, "haircare": 51344, "back": 51344, "track": 51344, "NYFW": 48549, "vegan": 48549, "potato": 48549, "chowder": 48549, "Central": 48199, "Park": 48199, "cherry": 48199, "blossoms": 48199, "updating": 48199, "luggage": 48136, "broadway": 48136, "workouts": 48136, "glimpse": 48136, "cooking": 47383, "bday": 46079, "celebration": 46079, "fun": 46079, "exchanging": 46079, "gifts": 46079, "productive": 43953, "influencer": 43953, "sunnies": 43953, "more": 43953, "One": 43507, "Second": 43507, "Day": 43507, "Year": 43507, "2021": 43507, "december": 42470, "staycation": 42470, "rockaway": 42470, "beach": 42470, "chill": 42470, "roomie": 42470, "creator": 42470, "Chelsea": 42256, "flea": 42256, "market": 42256, "5th": 42256, "ave": 42256, "deep": 42256, "pack": 42001, "me": 42001, "3": 42001, "weeks": 42001, "Europe": 42001, "Farfetch": 42001, "poconos": 41739, "w/": 41739, "hot": 41739, "tub": 41739, "games": 41739, "laughs": 41739, "west": 40921, "village": 40921, "Basquiat": 40921, "city": 40921, "vineyard": 40921, "nights": 40921, "texas": 40081, "exploring": 40081, "Houston": 40081, "Austin": 40081, "healthy": 40081, "gut": 40081, "travel": 40081, "necessities": 40081, "mechanical": 40081, "bull": 40081, "GRWM": 37730, "candlelight": 37730, "abba": 37730, "tribute": 37730, "art": 37730, "galleries": 37730, "LES": 37730, "few": 31746, "coolest": 31746, "rescue": 31746, "dogs": 31746, "wholesome": 31746, "moments": 31746, "Vlog": 29496, ":": 29496, "Florence": 29496, "horseback": 29496, "wine": 29496, "tasting": 29496, "luxury": 29496, "outlets": 29496, "uffizi": 29496, "gallery": 29496, "Get": 21009, "Ready": 21009, "With": 21009, "Me": 21009, "Iceland": 21009, "how": 21009, "we": 21009, "planned": 21009, "our": 21009, "catching": 21009, "up": 21009, "updates": 21009, "italy": 14436, "#": 10592, "shorts": 10592, "so": 8792, "excited": 8792, "vlogs": 8792, "\ud83e\udd70": 8792, "\ud83c\udf5d": 5644, "Summer": 4948}, "token_counts": {"|": 26, ",": 25, "in": 24, "life": 19, "my": 19, "!": 16, "&": 10, "week": 10, "NYC": 10, "days": 7, "a": 7, "weekend": 7, "with": 6, "for": 5, "friends": 5, "haul": 4, "spring": 4, "of": 4, "Italy": 3, "(": 3, ")": 3, "VLOG": 3, "shopping": 3, "getting": 3, "events": 3, "new": 3, "out": 3, "show": 3, "vlog": 3, "the": 3, "night": 3, "nyc": 3, "riding": 2, "trip": 2, "#": 2, "shorts": 2, "cooking": 2, "italy": 2, "flying": 2, "to": 2, "vacation": 2, "on": 2, "cleaning": 2, "day": 2, "exhibit": 2, "cat": 2, "home": 2, "laser": 2, "tattoo": 2, "removal": 2, "thrift": 2, "time": 2, "at": 2, "holiday": 2, "vlogmas": 2, "Vlog": 1, ":": 1, "Florence": 1, "horseback": 1, "wine": 1, "tasting": 1, "luxury": 1, "outlets": 1, "uffizi": 1, "gallery": 1, "Get": 1, "Ready": 1, "With": 1, "Me": 1, "Iceland": 1, "how": 1, "we": 1, "planned": 1, "our": 1, "catching": 1, "up": 1, "updates": 1, "Summer": 1, "\ud83c\udf5d": 1, "pack": 1, "me": 1, "3": 1, "weeks": 1, "Europe": 1, "Farfetch": 1, "prepping": 1, "lash": 1, "lift": 1, "so": 1, "excited": 1, "vlogs": 1, "\ud83e\udd70": 1, "Chelsea": 1, "flea": 1, "market": 1, "5th": 1, "ave": 1, "deep": 1, "productive": 1, "influencer": 1, "sunnies": 1, "more": 1, "west": 1, "village": 1, "Basquiat": 1, "city": 1, "vineyard": 1, "nights": 1, "Central": 1, "Park": 1, "cherry": 1, "blossoms": 1, "updating": 1, "beauty": 1, "products": 1, "brunches": 1, "outfits": 1, "sitting": 1, "luggage": 1, "broadway": 1, "workouts": 1, "glimpse": 1, "weather": 1, "internet": 1, "IRL": 1, "update": 1, "MET": 1, "date": 1, "emotional": 1, "GRWM": 1, "candlelight": 1, "abba": 1, "tribute": 1, "art": 1, "galleries": 1, "LES": 1, "rug": 1, "reveal": 1, "apartment": 1, "banksy": 1, "poconos": 1, "w/": 1, "hot": 1, "tub": 1, "games": 1, "laughs": 1, "NYFW": 1, "vegan": 1, "potato": 1, "chowder": 1, "bday": 1, "celebration": 1, "fun": 1, "exchanging": 1, "gifts": 1, "few": 1, "coolest": 1, "rescue": 1, "dogs": 1, "wholesome": 1, "moments": 1, "bf": 1, "holy": 1, "grail": 1, "haircare": 1, "back": 1, "track": 1, "taking": 1, "myself": 1, "quality": 1, "friends/family": 1, "+": 1, "snow": 1, "storm": 1, "lots": 1, "reading": 1, "espresso": 1, "martinis": 1, "One": 1, "Second": 1, "Day": 1, "Year": 1, "2021": 1, "prep": 1, "christmas": 1, "decorating": 1, "cookies": 1, "texas": 1, "exploring": 1, "Houston": 1, "Austin": 1, "healthy": 1, "gut": 1, "travel": 1, "necessities": 1, "mechanical": 1, "bull": 1, "december": 1, "staycation": 1, "rockaway": 1, "beach": 1, "chill": 1, "roomie": 1, "creator": 1, "movies": 1, "advent": 1, "calendar": 1, "live": 1, "mini": 1, "VLOGMAS": 1, "?": 1, "black": 1, "friday": 1, "hauls": 1, "winter": 1, "rooftop": 1, "bar": 1, "lights": 1}}