{"token_views": {"Whiplash": 403242, "Run": 562523, "Hide": 562523, "Fight": 562523, "Eye": 562523, "Storm": 562523, "Are": 578279, "Dead": 578279, "Zombie": 578279, "Survival": 578279, "Its": 578279, "Best": 578279, "King": 631376, "Man": 631376, "Surprisingly": 631376, "Fun": 631376, "Prequel": 631376, "Red": 642422, "Notice": 642422, "Safe": 642422, "Disposable": 642422, "Forgettable": 642422, "Entertainment": 642422, "Peacemaker": 664694, "Better": 664694, "Than": 664694, "Expected": 664694, "Everything": 694699, "Everywhere": 694699, "Once": 694699, "Reacher": 769402, "Really": 769402, "Production": 792697, "Hell": 792697, "Justice": 792697, "League": 792697, "Moon": 809823, "Knight": 809823, "Messy": 809823, "Waste": 809823, "Cool": 809823, "Character": 809823, "Batman": 855842, "Spoiler": 855842, "Free": 855842, "Review": 855842, "Thor": 917300, "Love": 917300, "And": 917300, "Thunder": 917300, "Redemption": 917300, "or": 917300, "Destruction": 917300, "Prey": 923907, "Spoil": 923907, "Idea": 923907, "Top": 953454, "Gun": 953454, "Maverick": 953454, "Jurassic": 1008055, "Dominion": 1008055, "Greed": 1008055, "Finds": 1008055, "Way": 1008055, "Book": 1080104, "Boba": 1080104, "Fett": 1080104, "Nothing": 1080104, "But": 1080104, "Content": 1080104, "CGI": 1101749, "Overload": 1101749, "Batwoman": 1145244, "Cancelled": 1145244, "Is": 1145244, "End": 1145244, "Doctor": 1196377, "Strange": 1196377, "In": 1196377, "Multiverse": 1196377, "Madness": 1196377, "Bit": 1196377, "Truth": 1237652, "About": 1237652, "``": 1237652, "Toxic": 1237652, "Fandoms": 1237652, "''": 1237652, "Northman": 1258452, "We": 1258452, "Need": 1258452, "Like": 1258452, "All": 1272978, "Star": 1276138, "Trek": 1276138, "Picard": 1276138, "No": 1276138, "Reviews": 1276138, "'m": 1276138, "Out": 1276138, "Uncharted": 1469644, "Could": 1469644, "Up": 1469644, "Ms": 1566798, "Marvel": 1566798, "NOT": 1566798, "Build": 1566798, "Hero": 1566798, "She-Hulk": 1581418, "Attorney": 1581418, "Law": 1581418, "LOL": 1581418, "Nope": 1581418, "Teach": 1629040, "Awful": 1629040, "Lessons": 1629040, "Morbius": 1635667, "Yup": 1635667, "Terrible": 1635667, "Good": 1693309, "Slap": 1726463, "Heard": 1726463, "Around": 1726463, "Rings": 1782975, "of": 1782975, "Power": 1782975, "War": 1782975, "For": 1782975, "Fandom": 1782975, "I": 1940832, "Drinker": 2051395, "Recommends": 2051395, "...": 2051395, "Us": 2207319, "?": 2386944, "To": 2490705, "More": 2534590, ":": 2534872, "Actors": 2542348, "Mess": 2666021, "!": 2726662, "World": 2734518, "At": 2854396, "They": 3098684, "This": 3873340, "How": 3960349, "It": 4681550, "Why": 5273137, "Suck": 5273137, "'s": 5312926, "Of": 5423483, ",": 5778067, "Movies": 6531589, "Modern": 7815485, "A": 9925511, "The": 15817389, "-": 28422274}, "token_counts": {"Prey": 1, "Spoil": 1, "Idea": 1, "Truth": 1, "About": 1, "``": 1, "Toxic": 1, "Fandoms": 1, "''": 1, "CGI": 1, "Overload": 1, "Top": 1, "Gun": 1, "Maverick": 1, "Everything": 1, "Everywhere": 1, "Once": 1, "She-Hulk": 1, "Attorney": 1, "Law": 1, "LOL": 1, "Nope": 1, "Moon": 1, "Knight": 1, "Messy": 1, "Waste": 1, "Cool": 1, "Character": 1, "Doctor": 1, "Strange": 1, "In": 1, "Multiverse": 1, "Madness": 1, "Bit": 1, "Reacher": 1, "Really": 1, "Batwoman": 1, "Cancelled": 1, "Is": 1, "End": 1, "Northman": 1, "We": 1, "Need": 1, "Like": 1, "Thor": 1, "Love": 1, "And": 1, "Thunder": 1, "Redemption": 1, "or": 1, "Destruction": 1, "Whiplash": 1, "Morbius": 1, "Yup": 1, "Terrible": 1, "Star": 1, "Trek": 1, "Picard": 1, "No": 1, "Reviews": 1, "'m": 1, "Out": 1, "Peacemaker": 1, "Better": 1, "Than": 1, "Expected": 1, "Actors": 1, "Slap": 1, "Heard": 1, "Around": 1, "Production": 1, "Hell": 1, "Justice": 1, "League": 1, "Ms": 1, "Marvel": 1, "NOT": 1, "Build": 1, "Hero": 1, "Teach": 1, "Awful": 1, "Lessons": 1, "Batman": 1, "Spoiler": 1, "Free": 1, "Review": 1, "Are": 1, "Dead": 1, "Zombie": 1, "Survival": 1, "Its": 1, "Best": 1, "King": 1, "Man": 1, "Surprisingly": 1, "Fun": 1, "Prequel": 1, "Uncharted": 1, "Could": 1, "Up": 1, "Jurassic": 1, "Dominion": 1, "Greed": 1, "Finds": 1, "Way": 1, "Rings": 1, "of": 1, "Power": 1, "War": 1, "For": 1, "Fandom": 1, "Book": 1, "Boba": 1, "Fett": 1, "Nothing": 1, "But": 1, "Content": 1, "Run": 1, "Hide": 1, "Fight": 1, "Eye": 1, "Storm": 1, "Red": 1, "Notice": 1, "Safe": 1, "Disposable": 1, "Forgettable": 1, "Entertainment": 1, "To": 2, "Good": 2, ":": 2, "All": 2, "!": 2, "Mess": 2, "More": 2, "?": 2, "I": 2, "World": 2, "They": 2, "Us": 2, "How": 3, "Why": 3, "Suck": 3, "Drinker": 3, "Recommends": 3, "...": 3, "At": 3, "This": 3, "Modern": 4, "Movies": 4, "It": 4, ",": 5, "'s": 5, "Of": 6, "A": 9, "The": 15, "-": 25}, "term_views": {"Whiplash": 403242, "Run": 562523, "Hide": 562523, "Fight": 562523, "Eye": 562523, "Storm": 562523, "Are": 578279, "Dead": 578279, "Zombie": 578279, "Survival": 578279, "Its": 578279, "Best": 578279, "King's": 631376, "Man": 631376, "Surprisingly": 631376, "Fun": 631376, "Prequel": 631376, "Red": 642422, "Notice": 642422, "Safe,": 642422, "Disposable,": 642422, "Forgettable": 642422, "Entertainment": 642422, "Peacemaker": 664694, "Better": 664694, "Than": 664694, "I": 664694, "Expected": 664694, "Everything": 694699, "Everywhere": 694699, "Once": 694699, "Reacher": 769402, "Really": 769402, "Production": 792697, "Hell": 792697, "Justice": 792697, "League": 792697, "Moon": 809823, "Knight": 809823, "Messy": 809823, "Waste": 809823, "Cool": 809823, "Character": 809823, "Batman": 855842, "Spoiler": 855842, "Free": 855842, "Review": 855842, "Thor": 917300, "Love": 917300, "And": 917300, "Thunder": 917300, "Redemption": 917300, "or": 917300, "Destruction?": 917300, "Prey": 923907, "Spoil": 923907, "Idea": 923907, "Top": 953454, "Gun:": 953454, "Maverick": 953454, "Jurassic": 1008055, "Dominion": 1008055, "Greed": 1008055, "Finds": 1008055, "Way": 1008055, "Book": 1080104, "Boba": 1080104, "Fett": 1080104, "Nothing": 1080104, "But": 1080104, "Content": 1080104, "CGI": 1101749, "Overload": 1101749, "Batwoman": 1145244, "Cancelled": 1145244, "Is": 1145244, "End!": 1145244, "Doctor": 1196377, "Strange": 1196377, "In": 1196377, "Multiverse": 1196377, "Madness": 1196377, "Bit": 1196377, "Truth": 1237652, "About": 1237652, "\"Toxic": 1237652, "Fandoms\"": 1237652, "Northman": 1258452, "We": 1258452, "Need": 1258452, "Like": 1258452, "All": 1272978, "Star": 1276138, "Trek": 1276138, "Picard": 1276138, "No": 1276138, "Reviews,": 1276138, "I'm": 1276138, "Out": 1276138, "Uncharted": 1469644, "Could": 1469644, "Up?": 1469644, "Ms": 1566798, "Marvel": 1566798, "NOT": 1566798, "Build": 1566798, "Hero": 1566798, "She-Hulk:": 1581418, "Attorney": 1581418, "Law": 1581418, "LOL,": 1581418, "Nope!": 1581418, "Teach": 1629040, "Awful": 1629040, "Lessons": 1629040, "Morbius": 1635667, "Yup,": 1635667, "Terrible": 1635667, "Good": 1693309, "Slap": 1726463, "Heard": 1726463, "Around": 1726463, "Rings": 1782975, "of": 1782975, "Power": 1782975, "War": 1782975, "For": 1782975, "Fandom": 1782975, "Drinker": 2051395, "Recommends...": 2051395, "Us": 2207319, "To": 2490705, "More": 2534590, "Actors": 2542348, "Mess": 2666021, "World": 2734518, "At": 2854396, "They": 3098684, "This": 3873340, "How": 3960349, "It's": 4681550, "Why": 5273137, "Suck": 5273137, "Of": 5423483, "Movies": 6531589, "Modern": 7815485, "A": 9925511, "The": 15817389, "-": 28422274}, "term_counts": {"Prey": 1, "Spoil": 1, "Idea": 1, "Truth": 1, "About": 1, "\"Toxic": 1, "Fandoms\"": 1, "CGI": 1, "Overload": 1, "Top": 1, "Gun:": 1, "Maverick": 1, "Everything": 1, "Everywhere": 1, "Once": 1, "She-Hulk:": 1, "Attorney": 1, "Law": 1, "LOL,": 1, "Nope!": 1, "Moon": 1, "Knight": 1, "Messy": 1, "Waste": 1, "Cool": 1, "Character": 1, "Doctor": 1, "Strange": 1, "In": 1, "Multiverse": 1, "Madness": 1, "Bit": 1, "Reacher": 1, "Really": 1, "Batwoman": 1, "Cancelled": 1, "Is": 1, "End!": 1, "Northman": 1, "We": 1, "Need": 1, "Like": 1, "Thor": 1, "Love": 1, "And": 1, "Thunder": 1, "Redemption": 1, "or": 1, "Destruction?": 1, "Whiplash": 1, "Morbius": 1, "Yup,": 1, "Terrible": 1, "Star": 1, "Trek": 1, "Picard": 1, "No": 1, "Reviews,": 1, "I'm": 1, "Out": 1, "Peacemaker": 1, "Better": 1, "Than": 1, "I": 1, "Expected": 1, "Actors": 1, "Slap": 1, "Heard": 1, "Around": 1, "Production": 1, "Hell": 1, "Justice": 1, "League": 1, "Ms": 1, "Marvel": 1, "NOT": 1, "Build": 1, "Hero": 1, "Teach": 1, "Awful": 1, "Lessons": 1, "Batman": 1, "Spoiler": 1, "Free": 1, "Review": 1, "Are": 1, "Dead": 1, "Zombie": 1, "Survival": 1, "Its": 1, "Best": 1, "King's": 1, "Man": 1, "Surprisingly": 1, "Fun": 1, "Prequel": 1, "Uncharted": 1, "Could": 1, "Up?": 1, "Jurassic": 1, "Dominion": 1, "Greed": 1, "Finds": 1, "Way": 1, "Rings": 1, "of": 1, "Power": 1, "War": 1, "For": 1, "Fandom": 1, "Book": 1, "Boba": 1, "Fett": 1, "Nothing": 1, "But": 1, "Content": 1, "Run": 1, "Hide": 1, "Fight": 1, "Eye": 1, "Storm": 1, "Red": 1, "Notice": 1, "Safe,": 1, "Disposable,": 1, "Forgettable": 1, "Entertainment": 1, "To": 2, "Good": 2, "All": 2, "Mess": 2, "More": 2, "World": 2, "They": 2, "Us": 2, "How": 3, "Why": 3, "Suck": 3, "Drinker": 3, "Recommends...": 3, "At": 3, "This": 3, "Modern": 4, "Movies": 4, "It's": 4, "Of": 6, "A": 9, "The": 15, "-": 25}}