{"token_views": {"Invitaci\u00f3n": 199, "del": 199, "Bio": 201, "Angel": 203, "Grille": 203, "Cafe": 203, "one": 215, "Biografia": 230, "Alfredo": 261, "Duarte": 261, "Taxco": 261, "Produce": 261, "Liza": 263, "Pereira": 263, "Founder": 263, "Unique": 263, "Sweets": 263, "LULA": 263, "John": 264, "Birrieria": 264, "Nava": 280, "La": 280, "Moishe": 280, "Alex": 297, "Cabrera": 297, "Lalo": 297, "restaurant": 297, "located": 297, "on": 297, "Maxwell": 297, "David": 299, "Troncoso": 299, "Chief": 299, "Excellence": 299, "Officer": 299, "LC": 299, "Food": 299, "Distributor": 299, "Marty": 301, "Castro": 301, "CEO": 301, "Central": 301, "Mrs.": 301, "Francisca": 301, "Philip": 301, "Luis": 302, "Gonzalez": 302, "Executive": 302, "Mago": 302, "Grill": 302, "Cantina": 302, "Beto": 342, "Huerta": 342, "Sebastian": 353, "Foods": 353, "Promo": 362, "Tello": 406, "Invite": 407, "Jessica": 429, "Perjes": 429, "co-owner": 429, "Tacotl\u00e1n": 429, "Rest": 429, "Mr.": 478, "Jose": 478, "Owner": 478, "Carnicerias": 478, "'s": 500, "(": 527, ")": 527, "Zaragoza": 528, "Isaac": 560, "Juan": 566, "Casa": 581, "Eric": 599, "Fernandez": 599, "Director": 599, "Latin": 599, "Division": 599, "Cheney": 599, "Brothers": 599, "Inc": 603, "Street": 639, "Souto": 706, "Jesus": 762, "Martinez": 762, "The": 762, "Outpost": 762, "Mexican": 762, "Eatery": 762, "BREAKING": 787, "NEWS": 787, "Historia": 861, "at": 898, "Jimenez": 956, ".": 1032, "Gilberto": 1037, "II": 1037, "NOTICIA": 1054, "DE": 1054, "\u00daLTIMA": 1054, "HORA": 1054, "Chef": 1064, "Supremo\u00ae": 1223, "President": 1259, "owner": 1305, "Halloween": 1537, "Dip": 1537, "Villase\u00f1or": 1639, "Chorizo": 1889, "Poblano": 1889, "&": 2008, "Chilaquiles": 2442, "Roja": 2442, "V": 2446, "Salsa": 2784, "Elotes": 2826, "Cotija": 2826, "and": 3017, "Cheese": 4363, "Chipotle": 5133, "y": 5133, "Frutas": 5133, "of": 5134, "de": 5643, "Interview": 5734, ",": 6050, ":": 6771, "Quesadillas": 7022, "Inspira": 7133, "with": 11002, "*": 13154}, "token_counts": {"David": 1, "Troncoso": 1, "Chief": 1, "Excellence": 1, "Officer": 1, "LC": 1, "Food": 1, "Distributor": 1, "Liza": 1, "Pereira": 1, "Founder": 1, "Unique": 1, "Sweets": 1, "LULA": 1, "Eric": 1, "Fernandez": 1, "Director": 1, "Latin": 1, "Division": 1, "Cheney": 1, "Brothers": 1, "Sebastian": 1, "Foods": 1, "Mr.": 1, "Jose": 1, "Owner": 1, "Carnicerias": 1, "John": 1, "Birrieria": 1, "Marty": 1, "Castro": 1, "CEO": 1, "Central": 1, "Nava": 1, "La": 1, "Moishe": 1, "Alfredo": 1, "Duarte": 1, "Taxco": 1, "Produce": 1, "Alex": 1, "Cabrera": 1, "Lalo": 1, "restaurant": 1, "located": 1, "on": 1, "Maxwell": 1, "Angel": 1, "Grille": 1, "Cafe": 1, "Beto": 1, "Huerta": 1, "Luis": 1, "Gonzalez": 1, "Executive": 1, "Mago": 1, "Grill": 1, "Cantina": 1, "Jesus": 1, "Martinez": 1, "The": 1, "Outpost": 1, "Mexican": 1, "Eatery": 1, "Jessica": 1, "Perjes": 1, "co-owner": 1, "Tacotl\u00e1n": 1, "Rest": 1, "Invite": 1, "Bio": 1, "Invitaci\u00f3n": 1, "del": 1, "Biografia": 1, "Mrs.": 1, "Francisca": 1, "Philip": 1, "one": 1, "Elotes": 1, "Cotija": 1, "Chorizo": 1, "Poblano": 1, "Chilaquiles": 1, "Roja": 1, "Halloween": 1, "Dip": 1, "Historia": 1, "BREAKING": 1, "NEWS": 1, "NOTICIA": 1, "DE": 1, "\u00daLTIMA": 1, "HORA": 1, "Chipotle": 1, "y": 1, "Frutas": 1, "at": 2, "(": 2, ")": 2, "Souto": 2, "Jimenez": 2, "Juan": 2, "Zaragoza": 2, "Casa": 2, "Isaac": 2, "Inc": 2, "'s": 2, "Street": 2, "Tello": 2, "Salsa": 2, "Chef": 2, "Promo": 2, "Cheese": 2, "Quesadillas": 2, "de": 3, ".": 3, "Supremo\u00ae": 3, "President": 4, "Gilberto": 4, "II": 4, "and": 5, "owner": 5, "&": 6, "Villase\u00f1or": 6, "V": 6, "of": 14, "*": 14, "Interview": 16, "with": 18, ",": 19, ":": 20, "Inspira": 22}, "term_views": {"Invitaci\u00f3n": 199, "del": 199, "Bio": 201, "Angel": 203, "Tello,": 203, "Tello's": 203, "Grille": 203, "Cafe": 203, "one": 215, "Biografia": 230, "Alfredo": 261, "Duarte,": 261, "Taxco": 261, "Produce": 261, "Liza": 263, "Pereira,": 263, "Founder": 263, "Unique": 263, "Sweets": 263, "(LULA)": 263, "(John)": 264, "Zaragoza,": 264, "Birrieria": 264, "Zaragoza": 264, "Nava,": 280, "La": 280, "Moishe": 280, "Alex": 297, "Cabrera,": 297, "Lalo's": 297, "restaurant": 297, "located": 297, "on": 297, "Maxwell": 297, "Street": 297, "David": 299, "Troncoso,": 299, "Chief": 299, "Excellence": 299, "Officer": 299, "LC": 299, "Food": 299, "Distributor": 299, "Marty": 301, "Castro,": 301, "CEO": 301, "Central": 301, "Mrs.": 301, "Francisca": 301, "Philip": 301, "Luis": 302, "Gonzalez,": 302, "Executive": 302, "Mago": 302, "Grill": 302, "Cantina": 302, "Beto": 342, "Huerta,": 342, "Street,": 342, "Sebastian": 353, "Souto,": 353, "Souto": 353, "Foods": 353, "Inspira": 362, "Promo": 362, "Invite": 407, "Jessica": 429, "Perjes,": 429, "co-owner": 429, "Tacotl\u00e1n": 429, "Rest.": 429, "Mr.": 478, "Jose": 478, "Jimenez,": 478, "Owner": 478, "Carnicerias": 478, "Jimenez": 478, "Isaac": 560, "Juan": 566, "Casa": 581, "Eric": 599, "Fernandez,": 599, "Director": 599, "Latin": 599, "Division": 599, "Cheney": 599, "Brothers": 599, "Villase\u00f1or": 602, "Inc.": 603, "Jesus": 762, "Martinez": 762, "The": 762, "Outpost": 762, "Mexican": 762, "Eatery": 762, "&": 785, "**BREAKING": 787, "NEWS****": 787, "Historia": 861, "at": 898, "Gilberto": 1037, "Villase\u00f1or,": 1037, "II": 1037, "**": 1054, "NOTICIA": 1054, "DE": 1054, "\u00daLTIMA": 1054, "HORA******": 1054, "Chef": 1064, "V&V": 1223, "Supremo\u00ae": 1223, "President": 1259, "owner": 1305, "Halloween": 1537, "Dip": 1537, "Chorizo": 1889, "Poblano": 1889, "Chilaquiles": 2442, "Roja": 2442, "Salsa": 2784, "Elotes": 2826, "Cotija": 2826, "and": 3017, "Cheese": 4363, "Chipotle": 5133, "y": 5133, "Frutas": 5133, "of": 5134, "de": 5643, "Interview": 5734, "Inspira:": 6771, "Quesadillas": 7022, "with": 11002}, "term_counts": {"David": 1, "Troncoso,": 1, "Chief": 1, "Excellence": 1, "Officer": 1, "LC": 1, "Food": 1, "Distributor": 1, "Liza": 1, "Pereira,": 1, "Founder": 1, "Unique": 1, "Sweets": 1, "(LULA)": 1, "Eric": 1, "Fernandez,": 1, "Director": 1, "Latin": 1, "Division": 1, "Cheney": 1, "Brothers": 1, "Sebastian": 1, "Souto,": 1, "Souto": 1, "Foods": 1, "Mr.": 1, "Jose": 1, "Jimenez,": 1, "Owner": 1, "Carnicerias": 1, "Jimenez": 1, "(John)": 1, "Zaragoza,": 1, "Birrieria": 1, "Zaragoza": 1, "Marty": 1, "Castro,": 1, "CEO": 1, "Central": 1, "Nava,": 1, "La": 1, "Moishe": 1, "Alfredo": 1, "Duarte,": 1, "Taxco": 1, "Produce": 1, "Alex": 1, "Cabrera,": 1, "Lalo's": 1, "restaurant": 1, "located": 1, "on": 1, "Maxwell": 1, "Street": 1, "Angel": 1, "Tello,": 1, "Tello's": 1, "Grille": 1, "Cafe": 1, "Beto": 1, "Huerta,": 1, "Street,": 1, "Luis": 1, "Gonzalez,": 1, "Executive": 1, "Mago": 1, "Grill": 1, "Cantina": 1, "Jesus": 1, "Martinez": 1, "The": 1, "Outpost": 1, "Mexican": 1, "Eatery": 1, "Jessica": 1, "Perjes,": 1, "co-owner": 1, "Tacotl\u00e1n": 1, "Rest.": 1, "Invite": 1, "Bio": 1, "Invitaci\u00f3n": 1, "del": 1, "Biografia": 1, "Mrs.": 1, "Francisca": 1, "Philip": 1, "one": 1, "Elotes": 1, "Cotija": 1, "Chorizo": 1, "Poblano": 1, "Chilaquiles": 1, "Roja": 1, "Halloween": 1, "Dip": 1, "Historia": 1, "**BREAKING": 1, "NEWS****": 1, "**": 1, "NOTICIA": 1, "DE": 1, "\u00daLTIMA": 1, "HORA******": 1, "Chipotle": 1, "y": 1, "Frutas": 1, "at": 2, "Juan": 2, "Casa": 2, "Isaac": 2, "Inc.": 2, "Salsa": 2, "Chef": 2, "Villase\u00f1or": 2, "Inspira": 2, "Promo": 2, "Cheese": 2, "Quesadillas": 2, "de": 3, "&": 3, "V&V": 3, "Supremo\u00ae": 3, "President": 4, "Gilberto": 4, "Villase\u00f1or,": 4, "II": 4, "and": 5, "owner": 5, "of": 14, "Interview": 16, "with": 18, "Inspira:": 20}}