{"Jeep": ["wyplhNnqazg"], ",": ["wyplhNnqazg", "7M2nfksgqAo", "SLzf3lbTgRw", "JO1tihW9PMc", "vFSMWCRUW5c", "mobuRkaOG9s", "njI-TqLpGxA", "nKnFBDDGgQk", "Jzs8TN3jXpY", "r67qr1Xuni8", "WLt6HZEgECM", "7VsXymZv3B0", "G7KNjsMsN0Q", "ERCgjFqyrCY", "cqp276-D884", "yfx1VLk3A8s", "KwyOOBI3s9Q", "hmgsYSFy6C8", "Bw0XwUFo5Ms", "HFraHcJgYnA", "LBcmpN79RCc", "SJ49ZOO3gIk", "qXycujueBeI", "awaFqFf4Si0", "_cheCxfQb_4", "4P8JMX2guNw", "qQiUyzyRkNk", "7cjXpUuuU-Y", "9RkZ4nJBDoo", "ZhHUylSOReo", "Wc-1_ZOuoXU", "STE109w4sXo", "-0u9AZoCHdY", "4ddUoFONjlg", "gLFGmMm9PQk", "-H-Hkbw0Ne8", "3EhDpGvZObU", "B_UOvzQe9vk", "OVo_pKNQ8dc", "ggBAI0AxjJA", "KiOBueOFPDI", "hXvJyHsNvxw", "Yf8EA9KcjRY", "WtcALulJ-uU", "cH-xupX3TRo", "ybEqtWt7YC0", "4x93iu8BR24", "5uo6iYDrr0Q", "BsXAvHjKZe4", "M1Qk-quksXY", "QSY2OscYNX8", "5EAzshYBRo8"], "Formation": ["wyplhNnqazg", "7M2nfksgqAo", "SLzf3lbTgRw", "JO1tihW9PMc", "vFSMWCRUW5c", "njI-TqLpGxA", "nKnFBDDGgQk"], "And": ["wyplhNnqazg", "7M2nfksgqAo", "vFSMWCRUW5c", "nKnFBDDGgQk", "r67qr1Xuni8", "WLt6HZEgECM", "yfx1VLk3A8s", "hmgsYSFy6C8", "HFraHcJgYnA", "LBcmpN79RCc", "SJ49ZOO3gIk", "awaFqFf4Si0", "4P8JMX2guNw", "4P8JMX2guNw", "7cjXpUuuU-Y", "ZhHUylSOReo", "Wc-1_ZOuoXU", "-0u9AZoCHdY", "4ddUoFONjlg", "-H-Hkbw0Ne8", "OVo_pKNQ8dc", "hXvJyHsNvxw", "Yf8EA9KcjRY", "2ZpBa6g3dds", "cH-xupX3TRo", "cH-xupX3TRo", "nEYNqKkFkUo", "6F-4U8Nf7xw"], "Uses": ["wyplhNnqazg", "vFSMWCRUW5c", "mobuRkaOG9s", "nKnFBDDGgQk", "WLt6HZEgECM"], "Cartoon": ["wyplhNnqazg", "7M2nfksgqAo", "Jzs8TN3jXpY", "r67qr1Xuni8", "WLt6HZEgECM", "7VsXymZv3B0", "ERCgjFqyrCY", "yfx1VLk3A8s", "HFraHcJgYnA", "LBcmpN79RCc", "SJ49ZOO3gIk", "qXycujueBeI", "awaFqFf4Si0", "_cheCxfQb_4", "4P8JMX2guNw", "qQiUyzyRkNk", "7cjXpUuuU-Y", "ZhHUylSOReo", "Wc-1_ZOuoXU", "STE109w4sXo", "gLFGmMm9PQk", "3EhDpGvZObU", "B_UOvzQe9vk", "ggBAI0AxjJA", "2ZpBa6g3dds", "YUwQHHpDoFE", "ybEqtWt7YC0", "4x93iu8BR24", "VBzLoFbPGDg", "5uo6iYDrr0Q", "BsXAvHjKZe4", "M1Qk-quksXY", "3hdqwdgalPU", "W-oox3j3-Ms", "5EAzshYBRo8"], "Videos": ["wyplhNnqazg", "7M2nfksgqAo", "SLzf3lbTgRw", "JO1tihW9PMc", "vFSMWCRUW5c", "njI-TqLpGxA", "Jzs8TN3jXpY", "r67qr1Xuni8", "WLt6HZEgECM", "7VsXymZv3B0", "ERCgjFqyrCY", "cqp276-D884", "yfx1VLk3A8s", "KwyOOBI3s9Q", "HFraHcJgYnA", "LBcmpN79RCc", "SJ49ZOO3gIk", "qXycujueBeI", "awaFqFf4Si0", "_cheCxfQb_4", "4P8JMX2guNw", "qQiUyzyRkNk", "7cjXpUuuU-Y", "ZhHUylSOReo", "Wc-1_ZOuoXU", "STE109w4sXo", "4ddUoFONjlg", "gLFGmMm9PQk", "-H-Hkbw0Ne8", "3EhDpGvZObU", "B_UOvzQe9vk", "ggBAI0AxjJA", "KiOBueOFPDI", "hXvJyHsNvxw", "Yf8EA9KcjRY", "2ZpBa6g3dds", "YUwQHHpDoFE", "ybEqtWt7YC0", "4x93iu8BR24", "VBzLoFbPGDg", "5uo6iYDrr0Q", "BsXAvHjKZe4", "M1Qk-quksXY", "3hdqwdgalPU", "W-oox3j3-Ms", "QSY2OscYNX8", "5EAzshYBRo8"], "for": ["wyplhNnqazg", "7M2nfksgqAo", "SLzf3lbTgRw", "JO1tihW9PMc", "vFSMWCRUW5c", "mobuRkaOG9s", "njI-TqLpGxA", "WLt6HZEgECM", "7VsXymZv3B0", "ERCgjFqyrCY", "cqp276-D884", "yfx1VLk3A8s", "hmgsYSFy6C8", "Bw0XwUFo5Ms", "SJ49ZOO3gIk", "qXycujueBeI", "7cjXpUuuU-Y", "9RkZ4nJBDoo", "gLFGmMm9PQk", "-H-Hkbw0Ne8", "OVo_pKNQ8dc", "KiOBueOFPDI", "hXvJyHsNvxw", "Yf8EA9KcjRY", "WtcALulJ-uU", "2ZpBa6g3dds", "cH-xupX3TRo", "ybEqtWt7YC0", "5uo6iYDrr0Q", "QSY2OscYNX8", "5EAzshYBRo8", "5EAzshYBRo8"], "Children": ["wyplhNnqazg", "SLzf3lbTgRw", "JO1tihW9PMc", "vFSMWCRUW5c", "mobuRkaOG9s", "njI-TqLpGxA", "cqp276-D884", "hmgsYSFy6C8", "Bw0XwUFo5Ms", "SJ49ZOO3gIk", "qXycujueBeI", "9RkZ4nJBDoo", "gLFGmMm9PQk", "OVo_pKNQ8dc", "KiOBueOFPDI", "hXvJyHsNvxw", "Yf8EA9KcjRY", "WtcALulJ-uU", "2ZpBa6g3dds", "cH-xupX3TRo", "ybEqtWt7YC0", "5uo6iYDrr0Q", "QSY2OscYNX8"], "Bike": ["7M2nfksgqAo"], "Car": ["7M2nfksgqAo", "SLzf3lbTgRw", "mobuRkaOG9s", "WLt6HZEgECM", "qXycujueBeI", "_cheCxfQb_4", "qQiUyzyRkNk", "7cjXpUuuU-Y", "Wc-1_ZOuoXU", "STE109w4sXo", "4ddUoFONjlg", "3EhDpGvZObU", "B_UOvzQe9vk", "OVo_pKNQ8dc", "ggBAI0AxjJA", "hXvJyHsNvxw", "Yf8EA9KcjRY", "2ZpBa6g3dds", "YUwQHHpDoFE", "ybEqtWt7YC0", "VBzLoFbPGDg", "W-oox3j3-Ms"], "Street": ["7M2nfksgqAo"], "Vehicles": ["7M2nfksgqAo"], "Kids": ["7M2nfksgqAo", "SLzf3lbTgRw", "JO1tihW9PMc", "vFSMWCRUW5c", "njI-TqLpGxA", "nKnFBDDGgQk", "Jzs8TN3jXpY", "WLt6HZEgECM", "7VsXymZv3B0", "ERCgjFqyrCY", "cqp276-D884", "cqp276-D884", "yfx1VLk3A8s", "KwyOOBI3s9Q", "hmgsYSFy6C8", "Bw0XwUFo5Ms", "HFraHcJgYnA", "awaFqFf4Si0", "qQiUyzyRkNk", "7cjXpUuuU-Y", "9RkZ4nJBDoo", "-0u9AZoCHdY", "-0u9AZoCHdY", "gLFGmMm9PQk", "-H-Hkbw0Ne8", "3EhDpGvZObU", "KiOBueOFPDI", "WtcALulJ-uU", "YUwQHHpDoFE", "LtTLK9zIP2U", "4x93iu8BR24", "nEYNqKkFkUo", "5uo6iYDrr0Q", "BsXAvHjKZe4", "M1Qk-quksXY", "6F-4U8Nf7xw", "6F-4U8Nf7xw", "W-oox3j3-Ms", "QSY2OscYNX8", "5EAzshYBRo8"], "Bulldozer": ["SLzf3lbTgRw"], "cartoon": ["SLzf3lbTgRw"], "by": ["SLzf3lbTgRw", "JO1tihW9PMc", "vFSMWCRUW5c", "njI-TqLpGxA", "nKnFBDDGgQk", "Jzs8TN3jXpY", "hmgsYSFy6C8", "Bw0XwUFo5Ms", "HFraHcJgYnA", "qQiUyzyRkNk", "9RkZ4nJBDoo", "-0u9AZoCHdY", "gLFGmMm9PQk", "3EhDpGvZObU", "KiOBueOFPDI", "WtcALulJ-uU", "YUwQHHpDoFE", "LtTLK9zIP2U", "4x93iu8BR24", "5uo6iYDrr0Q", "BsXAvHjKZe4", "M1Qk-quksXY", "6F-4U8Nf7xw", "W-oox3j3-Ms", "QSY2OscYNX8"], "Channel": ["SLzf3lbTgRw", "JO1tihW9PMc", "vFSMWCRUW5c", "njI-TqLpGxA", "nKnFBDDGgQk", "Jzs8TN3jXpY", "cqp276-D884", "hmgsYSFy6C8", "Bw0XwUFo5Ms", "HFraHcJgYnA", "awaFqFf4Si0", "qQiUyzyRkNk", "9RkZ4nJBDoo", "-0u9AZoCHdY", "gLFGmMm9PQk", "3EhDpGvZObU", "KiOBueOFPDI", "WtcALulJ-uU", "YUwQHHpDoFE", "LtTLK9zIP2U", "4x93iu8BR24", "5uo6iYDrr0Q", "BsXAvHjKZe4", "M1Qk-quksXY", "6F-4U8Nf7xw", "W-oox3j3-Ms", "QSY2OscYNX8"], "Garbage": ["JO1tihW9PMc"], "Truck": ["JO1tihW9PMc", "nKnFBDDGgQk", "qXycujueBeI", "_cheCxfQb_4", "7cjXpUuuU-Y", "ZhHUylSOReo", "Wc-1_ZOuoXU", "STE109w4sXo", "B_UOvzQe9vk", "OVo_pKNQ8dc", "ggBAI0AxjJA", "hXvJyHsNvxw", "Yf8EA9KcjRY", "WtcALulJ-uU", "WtcALulJ-uU", "2ZpBa6g3dds", "YUwQHHpDoFE", "ybEqtWt7YC0", "VBzLoFbPGDg", "W-oox3j3-Ms"], "Tractor": ["vFSMWCRUW5c"], "Learning": ["vFSMWCRUW5c", "4ddUoFONjlg", "-H-Hkbw0Ne8", "KiOBueOFPDI", "QSY2OscYNX8"], "Police": ["mobuRkaOG9s"], "Emergency": ["mobuRkaOG9s"], "Vehicle": ["mobuRkaOG9s"], "Ambulance": ["njI-TqLpGxA"], "Van": ["njI-TqLpGxA"], "Concrete": ["nKnFBDDGgQk"], "Mixer": ["nKnFBDDGgQk"], "Dinobees": ["Jzs8TN3jXpY"], "Funny": ["Jzs8TN3jXpY", "BsXAvHjKZe4"], "Animated": ["Jzs8TN3jXpY"], "Spooky": ["r67qr1Xuni8"], "Delivery": ["r67qr1Xuni8"], "Om": ["r67qr1Xuni8", "hmgsYSFy6C8", "awaFqFf4Si0", "BsXAvHjKZe4", "M1Qk-quksXY", "5EAzshYBRo8"], "Nom": ["r67qr1Xuni8", "hmgsYSFy6C8", "hmgsYSFy6C8", "awaFqFf4Si0", "BsXAvHjKZe4", "M1Qk-quksXY", "5EAzshYBRo8"], "Stories": ["r67qr1Xuni8", "yfx1VLk3A8s", "hmgsYSFy6C8", "SJ49ZOO3gIk", "awaFqFf4Si0", "4P8JMX2guNw", "7cjXpUuuU-Y", "5uo6iYDrr0Q", "3hdqwdgalPU", "5EAzshYBRo8"], "Cargo": ["WLt6HZEgECM"], "Airplane": ["WLt6HZEgECM"], "More": ["WLt6HZEgECM", "G7KNjsMsN0Q", "KwyOOBI3s9Q", "LtTLK9zIP2U", "VBzLoFbPGDg", "3hdqwdgalPU", "W-oox3j3-Ms"], "Rollerskate": ["7VsXymZv3B0"], "Gob": ["7VsXymZv3B0", "HFraHcJgYnA", "4P8JMX2guNw"], "and": ["7VsXymZv3B0", "gLFGmMm9PQk", "3hdqwdgalPU", "5EAzshYBRo8"], "Friends": ["7VsXymZv3B0", "HFraHcJgYnA", "4P8JMX2guNw"], "Let": ["G7KNjsMsN0Q", "ybEqtWt7YC0"], "'s": ["G7KNjsMsN0Q", "ybEqtWt7YC0"], "Scribble": ["G7KNjsMsN0Q"], "Rock": ["G7KNjsMsN0Q"], "Paper": ["G7KNjsMsN0Q"], "Scissors": ["G7KNjsMsN0Q"], "+": ["G7KNjsMsN0Q", "KwyOOBI3s9Q", "LtTLK9zIP2U", "VBzLoFbPGDg", "W-oox3j3-Ms"], "Nursery": ["G7KNjsMsN0Q", "LBcmpN79RCc", "-0u9AZoCHdY", "LtTLK9zIP2U", "cH-xupX3TRo", "nEYNqKkFkUo", "6F-4U8Nf7xw"], "Rhymes": ["G7KNjsMsN0Q", "ERCgjFqyrCY", "Bw0XwUFo5Ms", "LBcmpN79RCc", "9RkZ4nJBDoo", "ZhHUylSOReo", "Wc-1_ZOuoXU", "-0u9AZoCHdY", "4ddUoFONjlg", "LtTLK9zIP2U", "cH-xupX3TRo", "nEYNqKkFkUo", "6F-4U8Nf7xw"], "Hipporopopo": ["ERCgjFqyrCY"], "-": ["ERCgjFqyrCY"], "Songs": ["ERCgjFqyrCY", "-H-Hkbw0Ne8", "6F-4U8Nf7xw"], "&": ["ERCgjFqyrCY"], "Who": ["cqp276-D884"], "Gon": ["cqp276-D884"], "na": ["cqp276-D884"], "You": ["cqp276-D884", "6F-4U8Nf7xw"], "Call": ["cqp276-D884"], "Song": ["cqp276-D884", "KwyOOBI3s9Q", "STE109w4sXo", "-0u9AZoCHdY", "-0u9AZoCHdY", "4ddUoFONjlg", "gLFGmMm9PQk", "-H-Hkbw0Ne8", "3EhDpGvZObU", "ggBAI0AxjJA", "KiOBueOFPDI", "nEYNqKkFkUo", "QSY2OscYNX8"], "By": ["cqp276-D884"], "Libra": ["yfx1VLk3A8s"], "The": ["yfx1VLk3A8s", "KwyOOBI3s9Q", "qQiUyzyRkNk", "Wc-1_ZOuoXU", "ybEqtWt7YC0", "nEYNqKkFkUo", "nEYNqKkFkUo"], "Line": ["yfx1VLk3A8s"], "Astrolology": ["yfx1VLk3A8s", "4x93iu8BR24", "3hdqwdgalPU"], "Tv": ["yfx1VLk3A8s"], "Things": ["KwyOOBI3s9Q"], "In": ["KwyOOBI3s9Q"], "Sky": ["KwyOOBI3s9Q"], "Autumn": ["KwyOOBI3s9Q"], "Entertainment": ["KwyOOBI3s9Q"], "Sweet": ["hmgsYSFy6C8"], "Cafe": ["hmgsYSFy6C8"], "Merry": ["Bw0XwUFo5Ms"], "Tale": ["Bw0XwUFo5Ms"], "of": ["Bw0XwUFo5Ms", "B_UOvzQe9vk"], "a": ["Bw0XwUFo5Ms"], "Joyous": ["Bw0XwUFo5Ms"], "Christmas": ["Bw0XwUFo5Ms"], "X'mas": ["Bw0XwUFo5Ms"], "Run": ["HFraHcJgYnA", "4P8JMX2guNw"], "Competition": ["HFraHcJgYnA", "awaFqFf4Si0", "4P8JMX2guNw"], "2": ["HFraHcJgYnA"], "Scary": ["LBcmpN79RCc", "ZhHUylSOReo"], "Flying": ["LBcmpN79RCc"], "Shark": ["LBcmpN79RCc"], "Halloween": ["LBcmpN79RCc", "9RkZ4nJBDoo", "ZhHUylSOReo"], "Virgo": ["SJ49ZOO3gIk"], "Shhhh": ["SJ49ZOO3gIk"], "Atrolology": ["SJ49ZOO3gIk"], "Jack": ["qXycujueBeI", "9RkZ4nJBDoo"], "O": ["qXycujueBeI", "9RkZ4nJBDoo"], "'": ["qXycujueBeI", "9RkZ4nJBDoo"], "Lantern": ["qXycujueBeI", "9RkZ4nJBDoo"], "Monster": ["qXycujueBeI", "_cheCxfQb_4", "qQiUyzyRkNk", "7cjXpUuuU-Y", "ZhHUylSOReo", "Wc-1_ZOuoXU", "STE109w4sXo", "B_UOvzQe9vk", "OVo_pKNQ8dc", "ggBAI0AxjJA", "hXvJyHsNvxw", "Yf8EA9KcjRY", "WtcALulJ-uU", "2ZpBa6g3dds", "YUwQHHpDoFE", "ybEqtWt7YC0", "VBzLoFbPGDg", "W-oox3j3-Ms"], "Dan": ["qXycujueBeI", "7cjXpUuuU-Y", "STE109w4sXo", "B_UOvzQe9vk", "OVo_pKNQ8dc", "ggBAI0AxjJA", "ybEqtWt7YC0", "VBzLoFbPGDg"], "Hot": ["awaFqFf4Si0"], "Haunted": ["_cheCxfQb_4", "_cheCxfQb_4"], "Island": ["_cheCxfQb_4"], "House": ["_cheCxfQb_4"], "1": ["4P8JMX2guNw"], "We": ["qQiUyzyRkNk", "Wc-1_ZOuoXU"], "Are": ["qQiUyzyRkNk", "Wc-1_ZOuoXU", "6F-4U8Nf7xw"], "Trucks": ["qQiUyzyRkNk"], "Goal": ["7cjXpUuuU-Y"], "Finger": ["STE109w4sXo"], "Family": ["STE109w4sXo"], "Hello": ["-0u9AZoCHdY", "cH-xupX3TRo"], "World": ["-0u9AZoCHdY"], "Numbers": ["4ddUoFONjlg"], "Little": ["4ddUoFONjlg", "3EhDpGvZObU", "LtTLK9zIP2U"], "Red": ["4ddUoFONjlg", "3EhDpGvZObU", "hXvJyHsNvxw"], "Learn": ["gLFGmMm9PQk", "ybEqtWt7YC0", "VBzLoFbPGDg"], "Planets": ["gLFGmMm9PQk"], "ABC": ["-H-Hkbw0Ne8", "KiOBueOFPDI", "VBzLoFbPGDg", "QSY2OscYNX8"], "Turkey": ["3EhDpGvZObU"], "Clash": ["B_UOvzQe9vk"], "Giants": ["B_UOvzQe9vk"], "Boot": ["B_UOvzQe9vk"], "Camp": ["B_UOvzQe9vk"], "I": ["OVo_pKNQ8dc"], "am": ["OVo_pKNQ8dc"], "Cartoons": ["OVo_pKNQ8dc", "hXvJyHsNvxw", "Yf8EA9KcjRY"], "Music": ["OVo_pKNQ8dc", "cH-xupX3TRo"], "Colors": ["ggBAI0AxjJA", "ybEqtWt7YC0"], "Stunt": ["hXvJyHsNvxw", "Yf8EA9KcjRY", "WtcALulJ-uU", "2ZpBa6g3dds"], "Blue": ["WtcALulJ-uU"], "Stunts": ["YUwQHHpDoFE"], "|": ["YUwQHHpDoFE"], "3D": ["YUwQHHpDoFE"], "Five": ["LtTLK9zIP2U"], "Monkeys": ["LtTLK9zIP2U"], "Schoolies": ["LtTLK9zIP2U"], "Goodbye": ["cH-xupX3TRo"], "Leo": ["4x93iu8BR24"], "Photobomber": ["4x93iu8BR24"], "Wheels": ["nEYNqKkFkUo"], "On": ["nEYNqKkFkUo"], "Bus": ["nEYNqKkFkUo"], "Go": ["nEYNqKkFkUo"], "Round": ["nEYNqKkFkUo"], "with": ["VBzLoFbPGDg"], "Easter": ["5uo6iYDrr0Q", "BsXAvHjKZe4", "M1Qk-quksXY"], "Eggs": ["5uo6iYDrr0Q", "M1Qk-quksXY"], "With": ["BsXAvHjKZe4"], "If": ["6F-4U8Nf7xw"], "Happy": ["6F-4U8Nf7xw"], "Like": ["3hdqwdgalPU"], "Me": ["3hdqwdgalPU"], "Please": ["3hdqwdgalPU"], "!": ["3hdqwdgalPU"], "Garage": ["W-oox3j3-Ms"], "Phonics": ["QSY2OscYNX8"], "Nuts": ["5EAzshYBRo8"], "Coco": ["5EAzshYBRo8"]}