{"Copper": ["YOdhar2YyZY"], "Babylights": ["YOdhar2YyZY"], "and": ["YOdhar2YyZY", "eSMMwGD_FYg", "x3Vkhv-wCqo", "N4dFcm0EQFk"], "Balayage": ["YOdhar2YyZY", "l3Ij3BnkL5M"], "on": ["YOdhar2YyZY", "eSMMwGD_FYg", "tyJzAa8vLO4", "uA17Gv13mI4"], "a": ["YOdhar2YyZY", "OAfqQzcWgMM", "OXzJWwMCu0I", "s1i4eBPBtMM", "jf0yFU0Tc-Y"], "natural": ["YOdhar2YyZY"], "red": ["YOdhar2YyZY"], "head": ["YOdhar2YyZY"], "$": ["eSMMwGD_FYg"], "900": ["eSMMwGD_FYg"], "bleach": ["eSMMwGD_FYg"], "retouch": ["eSMMwGD_FYg"], "silver": ["eSMMwGD_FYg"], "colormelt": ["eSMMwGD_FYg"], "blonde": ["eSMMwGD_FYg", "T3f0cPZir64"], "platinum": ["eSMMwGD_FYg"], "hair": ["eSMMwGD_FYg", "OAfqQzcWgMM", "T3f0cPZir64", "xBRfxC6RT_Q", "vSkC6hQQxO4", "5EOWNZOLYJY", "gQ02GHHwVTs", "jf0yFU0Tc-Y"], "Blonding": ["B4vFeLBDlpM"], "Bleach": ["B4vFeLBDlpM", "N4dFcm0EQFk"], "Retouch": ["B4vFeLBDlpM"], "Hair": ["B4vFeLBDlpM", "2TeObvFsyJs", "x3Vkhv-wCqo", "YkkFvwmiDso", "V4ZVnhGVOY4", "3U2La5gKLUY", "XSWJpIYDCSs", "-olEQnYD8CQ", "-i1Wyc-9R4c", "PwGqKOIaztg", "4lZui8dPZTc", "uA17Gv13mI4", "MBw_vgAGpuY", "2vUXCrkV1IA"], "Hack": ["B4vFeLBDlpM"], "-": ["B4vFeLBDlpM", "x3Vkhv-wCqo", "N4dFcm0EQFk", "tyJzAa8vLO4", "-i1Wyc-9R4c", "gJ0vIF9UXKs"], "HOW": ["B4vFeLBDlpM", "N4dFcm0EQFk"], "TO": ["B4vFeLBDlpM", "N4dFcm0EQFk", "V4ZVnhGVOY4", "MBw_vgAGpuY"], "REMOVE": ["B4vFeLBDlpM"], "COTTON": ["B4vFeLBDlpM"], "FROM": ["B4vFeLBDlpM"], "HAIR": ["B4vFeLBDlpM", "N4dFcm0EQFk", "-CeINQWjmTQ"], "EASY": ["B4vFeLBDlpM", "-CeINQWjmTQ", "uA17Gv13mI4"], "AND": ["B4vFeLBDlpM"], "FAST": ["B4vFeLBDlpM"], "!": ["B4vFeLBDlpM", "2TeObvFsyJs", "l3Ij3BnkL5M", "tyJzAa8vLO4", "-i1Wyc-9R4c", "PwGqKOIaztg", "s1i4eBPBtMM", "4lZui8dPZTc", "vSkC6hQQxO4", "uA17Gv13mI4", "gQ02GHHwVTs"], "Going": ["2TeObvFsyJs"], "From": ["2TeObvFsyJs"], "Dark": ["2TeObvFsyJs"], "Brown": ["2TeObvFsyJs", "V4ZVnhGVOY4", "-olEQnYD8CQ"], "to": ["2TeObvFsyJs", "T3f0cPZir64", "V4ZVnhGVOY4", "tyJzAa8vLO4", "-olEQnYD8CQ", "gJ0vIF9UXKs", "s1i4eBPBtMM"], "Silver": ["2TeObvFsyJs"], "Platinum": ["2TeObvFsyJs"], "Blonde": ["2TeObvFsyJs", "N4dFcm0EQFk", "V4ZVnhGVOY4", "uA17Gv13mI4"], "is": ["2TeObvFsyJs"], "Not": ["2TeObvFsyJs"], "Easy": ["2TeObvFsyJs"], "7": ["x3Vkhv-wCqo"], "Best": ["x3Vkhv-wCqo"], "Extension": ["x3Vkhv-wCqo"], "Methods": ["x3Vkhv-wCqo"], "for": ["x3Vkhv-wCqo", "gQ02GHHwVTs"], "Thick": ["x3Vkhv-wCqo"], "Thin": ["x3Vkhv-wCqo"], "WHICH": ["x3Vkhv-wCqo"], "METHOD": ["x3Vkhv-wCqo"], "IS": ["x3Vkhv-wCqo"], "RIGHT": ["x3Vkhv-wCqo"], "FOR": ["x3Vkhv-wCqo"], "YOU": ["x3Vkhv-wCqo"], "?": ["x3Vkhv-wCqo"], "Removing": ["YkkFvwmiDso"], "Fusion": ["YkkFvwmiDso", "XSWJpIYDCSs"], "Bond": ["YkkFvwmiDso", "XSWJpIYDCSs"], "Extensions": ["YkkFvwmiDso", "XSWJpIYDCSs", "4lZui8dPZTc", "MBw_vgAGpuY", "2vUXCrkV1IA"], "Taking": ["OAfqQzcWgMM"], "blunt": ["OAfqQzcWgMM"], "haircut": ["OAfqQzcWgMM"], "into": ["OAfqQzcWgMM"], "long": ["OAfqQzcWgMM"], "with": ["OAfqQzcWgMM", "s1i4eBPBtMM", "uA17Gv13mI4"], "fusion": ["OAfqQzcWgMM"], "bond": ["OAfqQzcWgMM"], "extensions\ufffc": ["OAfqQzcWgMM"], "Tone": ["N4dFcm0EQFk"], "Gone": ["N4dFcm0EQFk"], "Wrong": ["N4dFcm0EQFk"], "\ud83d\ude31": ["N4dFcm0EQFk"], "[": ["N4dFcm0EQFk", "V4ZVnhGVOY4", "-CeINQWjmTQ", "uA17Gv13mI4", "MBw_vgAGpuY", "2vUXCrkV1IA"], "FIX": ["N4dFcm0EQFk"], "BANDING": ["N4dFcm0EQFk"], "MAJOR": ["N4dFcm0EQFk", "V4ZVnhGVOY4"], "TRANSFORMATION": ["N4dFcm0EQFk", "2vUXCrkV1IA"], "]": ["N4dFcm0EQFk", "V4ZVnhGVOY4", "-CeINQWjmTQ", "uA17Gv13mI4", "MBw_vgAGpuY", "2vUXCrkV1IA"], "Teasylights": ["l3Ij3BnkL5M", "-CeINQWjmTQ"], "without": ["l3Ij3BnkL5M"], "the": ["l3Ij3BnkL5M", "OXzJWwMCu0I"], "tease": ["l3Ij3BnkL5M"], "\ufffc": ["l3Ij3BnkL5M"], "Black": ["T3f0cPZir64", "-olEQnYD8CQ"], "dye": ["T3f0cPZir64"], "isn": ["T3f0cPZir64"], "\u2019": ["T3f0cPZir64", "-i1Wyc-9R4c"], "t": ["T3f0cPZir64"], "as": ["T3f0cPZir64"], "easy": ["T3f0cPZir64"], "you": ["T3f0cPZir64", "vSkC6hQQxO4"], "think": ["T3f0cPZir64"], "\ud83e\udd14": ["T3f0cPZir64"], "#": ["T3f0cPZir64"], "haircolor": ["T3f0cPZir64"], "haircolortransformation": ["T3f0cPZir64"], "Transformation": ["V4ZVnhGVOY4"], "COLOR": ["V4ZVnhGVOY4", "2vUXCrkV1IA"], "CORRECTION": ["V4ZVnhGVOY4"], "NATURAL": ["V4ZVnhGVOY4"], "PLATINUM": ["V4ZVnhGVOY4"], "BLONDE": ["V4ZVnhGVOY4"], "Technique": ["-CeINQWjmTQ"], "HALO": ["-CeINQWjmTQ"], "HIGHLIGHT": ["-CeINQWjmTQ"], "ON": ["-CeINQWjmTQ"], "DARK": ["-CeINQWjmTQ"], "100K": ["tyJzAa8vLO4", "3U2La5gKLUY"], "Giveaway": ["tyJzAa8vLO4"], "Watch": ["tyJzAa8vLO4", "jf0yFU0Tc-Y"], "my": ["tyJzAa8vLO4"], "latest": ["tyJzAa8vLO4"], "video": ["tyJzAa8vLO4"], "how": ["tyJzAa8vLO4", "jf0yFU0Tc-Y"], "enter": ["tyJzAa8vLO4"], "My": ["3U2La5gKLUY"], "Favorite": ["3U2La5gKLUY"], "Professional": ["3U2La5gKLUY"], "Products": ["3U2La5gKLUY"], "+": ["3U2La5gKLUY", "2vUXCrkV1IA"], "SUBSCRIBER": ["3U2La5gKLUY"], "GIVEAWAY": ["3U2La5gKLUY"], "Client": ["OXzJWwMCu0I"], "wants": ["OXzJWwMCu0I"], "BIG": ["OXzJWwMCu0I"], "change": ["OXzJWwMCu0I"], "but": ["OXzJWwMCu0I"], "only": ["OXzJWwMCu0I"], "an": ["OXzJWwMCu0I"], "inch": ["OXzJWwMCu0I"], "off": ["OXzJWwMCu0I"], "ends": ["OXzJWwMCu0I"], "\ud83d\ude29": ["OXzJWwMCu0I"], "Individual": ["XSWJpIYDCSs"], "Custom": ["xBRfxC6RT_Q"], "colored": ["xBRfxC6RT_Q"], "handtied": ["xBRfxC6RT_Q"], "weft": ["xBRfxC6RT_Q", "jf0yFU0Tc-Y"], "extensions": ["xBRfxC6RT_Q", "vSkC6hQQxO4", "jf0yFU0Tc-Y"], "Box": ["-olEQnYD8CQ"], "Dye": ["-olEQnYD8CQ"], "Removal": ["-olEQnYD8CQ"], "Pro": ["-i1Wyc-9R4c"], "vs": ["-i1Wyc-9R4c"], "Drug": ["-i1Wyc-9R4c"], "Store": ["-i1Wyc-9R4c"], "Brands": ["-i1Wyc-9R4c"], "THEY": ["-i1Wyc-9R4c"], "RE": ["-i1Wyc-9R4c"], "NOT": ["-i1Wyc-9R4c"], "THE": ["-i1Wyc-9R4c"], "SAME": ["-i1Wyc-9R4c"], "5": ["gJ0vIF9UXKs"], "Updos": ["gJ0vIF9UXKs"], "Hairstyles": ["gJ0vIF9UXKs"], "Learn": ["gJ0vIF9UXKs"], "How": ["gJ0vIF9UXKs", "s1i4eBPBtMM"], "Upstyle": ["gJ0vIF9UXKs"], "Tinsel": ["PwGqKOIaztg", "4lZui8dPZTc", "MBw_vgAGpuY", "gQ02GHHwVTs"], "that": ["PwGqKOIaztg", "gQ02GHHwVTs"], "lasts": ["PwGqKOIaztg"], "TWO": ["PwGqKOIaztg"], "MONTHS": ["PwGqKOIaztg"], "add": ["s1i4eBPBtMM"], "tinsel": ["s1i4eBPBtMM"], "slip": ["s1i4eBPBtMM"], "knot": ["s1i4eBPBtMM"], "comes": ["4lZui8dPZTc"], "in": ["4lZui8dPZTc"], "all": ["4lZui8dPZTc"], "colors": ["4lZui8dPZTc"], "Why": ["vSkC6hQQxO4"], "should": ["vSkC6hQQxO4"], "wash": ["vSkC6hQQxO4"], "before": ["vSkC6hQQxO4"], "coloring": ["vSkC6hQQxO4"], "them": ["vSkC6hQQxO4"], "Breaking": ["uA17Gv13mI4"], "Up": ["uA17Gv13mI4"], "Harsh": ["uA17Gv13mI4"], "Lines": ["uA17Gv13mI4"], "Tutorial": ["uA17Gv13mI4"], "Highlights": ["uA17Gv13mI4"], "&": ["uA17Gv13mI4"], "Base": ["uA17Gv13mI4"], "Break": ["uA17Gv13mI4"], "TECHNIQUE": ["uA17Gv13mI4"], "3": ["MBw_vgAGpuY"], "WAYS": ["MBw_vgAGpuY"], "ADD": ["MBw_vgAGpuY"], "TINSEL": ["MBw_vgAGpuY"], "YOUR": ["MBw_vgAGpuY"], "HAIRSTYLE": ["MBw_vgAGpuY"], "The": ["5EOWNZOLYJY"], "cost": ["5EOWNZOLYJY"], "of": ["5EOWNZOLYJY"], "extension": ["5EOWNZOLYJY"], "move": ["5EOWNZOLYJY", "jf0yFU0Tc-Y"], "up": ["5EOWNZOLYJY", "jf0yFU0Tc-Y"], "appointment": ["5EOWNZOLYJY"], "Quick": ["2vUXCrkV1IA"], "20": ["2vUXCrkV1IA"], "Foil": ["2vUXCrkV1IA"], "Color": ["2vUXCrkV1IA"], "Correction": ["2vUXCrkV1IA"], "Volume": ["2vUXCrkV1IA"], "WITH": ["2vUXCrkV1IA"], "WEFT": ["2vUXCrkV1IA"], "EXTENSIONS": ["2vUXCrkV1IA"], "will": ["gQ02GHHwVTs"], "last": ["gQ02GHHwVTs"], "2": ["gQ02GHHwVTs"], "months": ["gQ02GHHwVTs"], "I": ["jf0yFU0Tc-Y"], "do": ["jf0yFU0Tc-Y"], "every": ["jf0yFU0Tc-Y"], "six": ["jf0yFU0Tc-Y"], "weeks": ["jf0yFU0Tc-Y"]}