{"frisbee": ["sOimo5qYJl8", "sa07jayw__A"], "laptop": ["DZaOFPMv8vk"], "person": ["DZaOFPMv8vk", "kI1VdgLRt_0", "zGSVmRm_T60", "nmb8ISbnhsQ", "C_BVcSneVmk", "ip1rbh1nWGA", "WUAjHv1WlJ8", "7DDYh1PlFEQ", "QPI1CjUFblY", "nJUY2c_u5bY", "KshiloOCymo", "IKTCssz2kew", "gRODQIg-2i0", "Bw2LxWGOX6E", "NFoPXpgV6iI", "QxxIVH5ca6M", "C9BJCSNWDAo", "r0CcHCwMMHU", "KZC6b-m2NaI"], "cell phone": ["kI1VdgLRt_0", "W4VOW5x6ufE", "1MOKaoG2t7I", "r0CcHCwMMHU"], "tv": ["zGSVmRm_T60", "C_BVcSneVmk", "WUAjHv1WlJ8", "7DDYh1PlFEQ", "IKTCssz2kew", "NFoPXpgV6iI", "QxxIVH5ca6M", "ahbPgacACRw"], "boat": ["jluDHpJlkxI"], "bird": ["0x8uVuBNBE0"], "bench": ["0x8uVuBNBE0"], "potted plant": ["C_BVcSneVmk", "gRODQIg-2i0"], "book": ["ip1rbh1nWGA", "nJUY2c_u5bY", "gRODQIg-2i0"], "chair": ["WUAjHv1WlJ8", "gRODQIg-2i0"], "tie": ["WUAjHv1WlJ8", "C9BJCSNWDAo"]}