{"person": ["g1hfbqdxuTY", "cj7ZNfkiYQ4", "CVDO1_rTaMA", "B1JpBUjJV2A", "Uzsaizuf93k", "V7FVLagh3vA", "CUFdcUD7hN0", "_mvuhZ8AoHo", "59f9FChsB80", "zFcEUCCgwtA", "ye-I0ry4bw4", "oMV9QbS_FLs", "4dHCMf8fU9Q", "Z-bSCHiRPvA", "pBk2njEwi5c", "z2HJFJN0C08", "84q1vsCZnSk", "tW-T886T0vM", "AYJUxIhFDrM", "vWKxg7nSmFc", "4XcaKZ0OxtE", "6Qgypa2VPbw", "6sfu2ht8ens", "2HzA511rIDg", "8Zzzl19aWT4", "v2Gol9gR_ZI", "4b2P-SC3rfI", "NNBfbMt1ulY", "FZ1HBsFxPIY"], "car": ["g1hfbqdxuTY", "oMV9QbS_FLs"], "cup": ["cj7ZNfkiYQ4"], "bed": ["B1JpBUjJV2A", "59f9FChsB80", "pBk2njEwi5c", "6Qgypa2VPbw", "6sfu2ht8ens", "8Zzzl19aWT4", "v2Gol9gR_ZI", "KP_HRhbl4fg", "4b2P-SC3rfI"], "tv": ["CUFdcUD7hN0", "84q1vsCZnSk", "4XcaKZ0OxtE"], "tie": ["CUFdcUD7hN0"], "horse": ["_mvuhZ8AoHo"], "chair": ["59f9FChsB80", "4dHCMf8fU9Q", "tW-T886T0vM"], "banana": ["ye-I0ry4bw4"], "dog": ["ye-I0ry4bw4"], "tennis racket": ["oMV9QbS_FLs"], "bottle": ["Z-bSCHiRPvA"], "suitcase": ["z2HJFJN0C08", "FZ1HBsFxPIY"], "umbrella": ["AYJUxIhFDrM"], "teddy bear": ["vWKxg7nSmFc", "v2Gol9gR_ZI"], "cell phone": ["2HzA511rIDg"]}