{"object_views": {"person": 23900542, "stop sign": 7446716, "cup": 5630182, "tv": 3956530, "chair": 2668483, "cell phone": 1089245, "car": 907096, "dining table": 738693, "bench": 667077, "potted plant": 644094, "baseball bat": 527441, "tie": 447740, "clock": 382919, "bowl": 205061, "carrot": 205061, "dog": 171698, "toothbrush": 116654}, "object_counts": {"person": 29, "stop sign": 5, "car": 3, "tv": 3, "bench": 3, "clock": 2, "cup": 2, "chair": 2, "tie": 2, "cell phone": 2, "baseball bat": 1, "toothbrush": 1, "bowl": 1, "carrot": 1, "dining table": 1, "dog": 1, "potted plant": 1}}