{"object_views": {"person": 10171, "tv": 3756, "bird": 2686, "potted plant": 2557, "book": 1580, "vase": 1453, "couch": 754, "dining table": 585, "umbrella": 569, "chair": 502, "bowl": 441, "cup": 354, "clock": 266, "sink": 198, "oven": 198, "apple": 198, "bottle": 194}, "object_counts": {"person": 26, "potted plant": 10, "tv": 5, "couch": 4, "vase": 3, "dining table": 3, "bowl": 3, "umbrella": 2, "chair": 2, "book": 2, "cup": 2, "clock": 1, "bird": 1, "sink": 1, "oven": 1, "apple": 1, "bottle": 1}}